feature_selection_lofo/__init__.py
feature_selection_lofo/lofo.py
feature_selection_lofo-0.0.6.dist-info/METADATA
feature_selection_lofo-0.0.6.dist-info/WHEEL
feature_selection_lofo-0.0.6.dist-info/licenses/LICENSE
feature_selection_lofo-0.0.6.dist-info/RECORD
