Metadata-Version: 2.1
Name: feature_selection_lofo
Version: 0.0.6
Summary: This is an implementation of LOFO for automatic feature selection.
Project-URL: Homepage, https://github.com/Azzam-Radman/LOFO
Project-URL: Bug Tracker, https://github.com/Azzam-Radman/LOFO/issues
Author-email: Azzam Radman <azzamradman1993@gmail.com>
License: MIT License
License-File: LICENSE
Classifier: License :: OSI Approved :: MIT License
Classifier: Operating System :: OS Independent
Classifier: Programming Language :: Python :: 3
Requires-Python: >=3.7
